{"type":"FeatureCollection","features":[{"type":"Feature","properties":{"osm_id":-2838155,"boundary":"administrative","admin_level":10,"parents":"-8853746,-1846690,-7327976,-1563319,-153545,-286393","name":"Martín Miguel de Guemes","local_name":"Martín Miguel de Guemes","name_en":null},"geometry":{"type":"MultiPolygon","coordinates":[[[[-65.7617875,-28.4667927],[-65.7612346,-28.4667191],[-65.7607265,-28.4666729],[-65.7604459,-28.4664512],[-65.7597928,-28.4642465],[-65.7608213,-28.4638918],[-65.7614103,-28.4649475],[-65.7614868,-28.465473],[-65.7617875,-28.4667927]]]]}}],"properties":{"osm_id":-8853746,"boundary":"administrative","admin_level":9,"parents":"-1846690,-7327976,-1563319,-153545,-286393","name":"Jorge Bermudez","local_name":"Jorge Bermudez","name_en":null}}