{"type":"FeatureCollection","features":[{"type":"Feature","properties":{"osm_id":-8193787,"boundary":"administrative","admin_level":11,"parents":"-3892612,-3594027,-3368048,-9404084,-153543,-286393","name":"Victoria Walsh","local_name":"Victoria Walsh","name_en":null},"geometry":{"type":"MultiPolygon","coordinates":[[[[-60.6899314,-32.9649481],[-60.6891839,-32.9649288],[-60.6884564,-32.9649101],[-60.6883624,-32.9643509],[-60.6897174,-32.9641405],[-60.6899314,-32.9649481]]]]}}],"properties":{"osm_id":-3892612,"boundary":"administrative","admin_level":10,"parents":"-3594027,-3368048,-9404084,-153543,-286393","name":"Bella Vista","local_name":"Bella Vista","name_en":null}}