{"type":"FeatureCollection","features":[{"type":"Feature","properties":{"osm_id":-2730170,"boundary":"administrative","admin_level":8,"parents":"-7256289,-3059853,-2405230,-286393","name":"Met치n","local_name":"Met치n","name_en":null},"geometry":{"type":"MultiPolygon","coordinates":[[[[-64.9931177,-25.5194427],[-64.9503245,-25.5194932],[-64.950263,-25.4770861],[-64.9930562,-25.4770355],[-64.9931177,-25.5194427]]]]}}],"properties":{"osm_id":-7256289,"boundary":"administrative","admin_level":7,"parents":"-3059853,-2405230,-286393","name":"Municipio de Met치n","local_name":"Municipio de Met치n","name_en":null}}